{"response": [{"Event":{"id":"1380","orgc_id":"25","org_id":"1","date":"2017-02-07","threat_level_id":"3","info":"WordPress REST API Vulnerability Abused in Defacement Campaigns","published":true,"uuid":"589a2956-febc-47e9-900b-1687c0a8ab16","attribute_count":"8","analysis":"2","timestamp":"1486498237","distribution":"3","proposal_email_lock":false,"locked":false,"publish_timestamp":"1697567868","sharing_group_id":"0","disable_correlation":false,"extends_uuid":"","protected":null,"event_creator_email":"admin@admin.test","Org":{"id":"1","name":"ORGNAME","uuid":"d874daa4-e17f-4ff7-8f84-7e0b2af5b311","local":true},"Orgc":{"id":"25","name":"CUDESO","uuid":"56c42374-fdb8-4544-a218-41ffc0a8ab16","local":false},"Attribute":[{"id":"276235","type":"link","category":"External analysis","to_ids":false,"uuid":"589a296a-1dcc-4029-bef8-1689c0a8ab16","event_id":"1380","distribution":"5","timestamp":"1486498154","comment":"","sharing_group_id":"0","deleted":false,"disable_correlation":false,"object_id":"0","object_relation":null,"first_seen":null,"last_seen":null,"value":"https://blog.sucuri.net/2017/02/wordpress-rest-api-vulnerability-abused-in-defacement-campaigns.html","Galaxy":[],"ShadowAttribute":[]},{"id":"276236","type":"ip-src","category":"Network activity","to_ids":true,"uuid":"589a29b1-03e0-4538-b149-1455c0a8ab16","event_id":"1380","distribution":"5","timestamp":"1486498225","comment":"","sharing_group_id":"0","deleted":false,"disable_correlation":false,"object_id":"0","object_relation":null,"first_seen":null,"last_seen":null,"value":"176.9.36.102","Galaxy":[],"ShadowAttribute":[]},{"id":"276237","type":"ip-src","category":"Network activity","to_ids":true,"uuid":"589a29b1-8b68-4819-8ae6-1455c0a8ab16","event_id":"1380","distribution":"5","timestamp":"1486498225","comment":"","sharing_group_id":"0","deleted":false,"disable_correlation":false,"object_id":"0","object_relation":null,"first_seen":null,"last_seen":null,"value":"185.116.213.71","Galaxy":[],"ShadowAttribute":[]},{"id":"276238","type":"ip-src","category":"Network activity","to_ids":true,"uuid":"589a29b1-b318-46eb-9401-1455c0a8ab16","event_id":"1380","distribution":"5","timestamp":"1486498225","comment":"","sharing_group_id":"0","deleted":false,"disable_correlation":false,"object_id":"0","object_relation":null,"first_seen":null,"last_seen":null,"value":"134.213.54.163","Galaxy":[],"ShadowAttribute":[]},{"id":"276239","type":"ip-src","category":"Network activity","to_ids":true,"uuid":"589a29b1-72f0-45aa-8b5f-1455c0a8ab16","event_id":"1380","distribution":"5","timestamp":"1486498225","comment":"","sharing_group_id":"0","deleted":false,"disable_correlation":false,"object_id":"0","object_relation":null,"first_seen":null,"last_seen":null,"value":"2a00:1a48:7808:104:9b57:dda6:eb3c:61e1","Galaxy":[],"ShadowAttribute":[]},{"id":"276240","type":"ip-src","category":"Network activity","to_ids":true,"uuid":"589a29b1-53ac-439a-a8a5-1455c0a8ab16","event_id":"1380","distribution":"5","timestamp":"1486498225","comment":"","sharing_group_id":"0","deleted":false,"disable_correlation":false,"object_id":"0","object_relation":null,"first_seen":null,"last_seen":null,"value":"37.237.192.22","Galaxy":[],"ShadowAttribute":[]},{"id":"276241","type":"ip-src","category":"Network activity","to_ids":true,"uuid":"589a29b1-946c-4c3e-8b5a-1455c0a8ab16","event_id":"1380","distribution":"5","timestamp":"1486498225","comment":"","sharing_group_id":"0","deleted":false,"disable_correlation":false,"object_id":"0","object_relation":null,"first_seen":null,"last_seen":null,"value":"144.217.81.160","Galaxy":[],"ShadowAttribute":[]},{"id":"276242","type":"link","category":"External analysis","to_ids":false,"uuid":"589a29bd-c374-4a9e-b7dd-1685c0a8ab16","event_id":"1380","distribution":"5","timestamp":"1486498237","comment":"","sharing_group_id":"0","deleted":false,"disable_correlation":false,"object_id":"0","object_relation":null,"first_seen":null,"last_seen":null,"value":"https://blog.sucuri.net/2017/02/content-injection-vulnerability-wordpress-rest-api.html","Galaxy":[],"ShadowAttribute":[]}],"ShadowAttribute":[],"RelatedEvent":[{"Event":{"id":"1","date":"2023-10-17","threat_level_id":"1","info":"Lab Demo","published":false,"uuid":"b5de5527-5af1-496c-8b93-9bdc351a0f15","analysis":"0","timestamp":"1697563645","distribution":"1","org_id":"1","orgc_id":"1","Org":{"id":"1","name":"ORGNAME","uuid":"d874daa4-e17f-4ff7-8f84-7e0b2af5b311"},"Orgc":{"id":"1","name":"ORGNAME","uuid":"d874daa4-e17f-4ff7-8f84-7e0b2af5b311"}}}],"Galaxy":[],"Object":[],"EventReport":[],"CryptographicKey":[],"Tag":[{"id":"9","name":"tlp:white","colour":"#ffffff","exportable":true,"user_id":"0","hide_tag":false,"numerical_value":null,"is_galaxy":false,"is_custom_galaxy":false,"local_only":false,"local":0,"relationship_type":null}]}}]}
